{"title":"对称点坐标","slug":"对称点坐标","date":"2021-09-04T10:09:59.107Z","updated":"2021-09-04T10:09:59.107Z","comments":true,"path":"api/articles/对称点坐标.json","excerpt":"问题描述​    在平面直角坐标系中,有一条直线$l: Ax+By+C=0$,(注:方程$Ax+By+C=0$和解析式$y=- \\frac{A}{B} x-\\frac{C}{B}$在$B\\ne 0$时等价 )和一给定点$P(\\alpha,\\beta )$,求$P$点关于直线$l$的对称点的坐标 [Figure] ","covers":["https://s1.ax1x.com/2020/07/30/auHbKH.png","https://s1.ax1x.com/2020/08/01/aGm0nP.png"],"content":"<link rel=\"stylesheet\" type=\"text&#x2F;css\" href=\"https://cdn.jsdelivr.net/npm/hexo-tag-hint@0.3.1/dist/hexo-tag-hint.min.css\"><h3 id=\"问题描述\"><a href=\"#问题描述\" class=\"headerlink\" title=\"问题描述\"></a>问题描述</h3><p>​    在平面直角坐标系中,有一条直线$l: Ax+By+C=0$,(注:方程$Ax+By+C=0$和解析式$y=- \\frac{A}{B} x-\\frac{C}{B}$在$B\\ne 0$时等价 )和一给定点$P(\\alpha,\\beta )$,求$P$点关于直线$l$的对称点的坐标</p>\n<p><img src=\"https://s1.ax1x.com/2020/07/30/auHbKH.png\" style=\"zoom: 15%;\" /></p>\n<span id=\"more\"></span>\n<hr>\n<h3 id=\"问题解决\"><a href=\"#问题解决\" class=\"headerlink\" title=\"问题解决\"></a>问题解决</h3><p>​    作$P$点关于$l$的对称点$P’$,并过$PP’$点作直线$l_{2}$,如下图:</p>\n<p><img src=\"https://s1.ax1x.com/2020/08/01/aGm0nP.png\" style=\"zoom:15%;\" /></p>\n<p>​    可知直线$l_{2}$垂直平分$l$,令$l_{2}$交$l$于$M$,只要计算出$M$点的坐标即可通过<span id=\"inline-blue\">中点坐标公式</span>计算出$P’$的坐标</p>\n<blockquote>\n<p><strong>中点坐标公式</strong></p>\n<p>若$M$是$P$与$P’$的中点,则$M$点满足:</p>\n<script type=\"math/tex; mode=display\">M=\\frac{P+P'}{2}</script><p>此式中的字母表示该点的相应坐标(或者说表示从原点到该点的向量),此式在任意维度的坐标系中都成立.</p>\n</blockquote>\n<p>​    我们知道互相垂直的两条直线的斜率互为负倒数,所以由$l$的斜率为 $-\\frac{A}{B}$ ,可以知道 $l_{2}$ 的斜率 $k_{PP’}= \\frac{B}{A}$</p>\n<p>​    所以$l_{2}$的点斜式为 $l_{2} :y-B=\\frac{B}{A}(x-\\alpha )$,把点斜式化为一般式并与$l$联立得:</p>\n<script type=\"math/tex; mode=display\">\\left\\{\\begin{matrix} \n  Bx-Ay+a +(A\\beta -B\\alpha )=0 \\\\  \n  Ax+By+C=0 \n\\end{matrix}\\right.</script><p>​    解这个方程组,结果即为$M$的坐标.</p>\n<p>方程组的解为:</p>\n<script type=\"math/tex; mode=display\">x=\\frac{B^{2}\\alpha -AC-AB\\beta }{A^{2}+B^{2}}\ny=\\frac{A^{2}\\beta-BC-AB\\alpha }{A^{2}+B^{2}}</script><p>则$M$点的坐标为:</p>\n<script type=\"math/tex; mode=display\">M(\\frac{B^{2}\\alpha -AC-AB\\beta }{A^{2}+B^{2}}\n,\\frac{A^{2}\\beta-BC-AB\\alpha }{A^{2}+B^{2}}  )</script><p>带入中点坐标公式,得$P’$的坐标为:</p>\n<script type=\"math/tex; mode=display\">P'(2x_{M}-\\alpha,2y_{M}-\\beta)</script><h3 id=\"总结\"><a href=\"#总结\" class=\"headerlink\" title=\"总结\"></a>总结</h3><blockquote>\n<p><span id=\"inline-purple\">垂足坐标公式</span></p>\n<script type=\"math/tex; mode=display\">M(\\frac{B^{2}\\alpha -AC-AB\\beta }{A^{2}+B^{2}}\n,\\frac{A^{2}\\beta-BC-AB\\alpha }{A^{2}+B^{2}}  )</script><p><span id=\"inline-purple\">对称点坐标公式</span></p>\n<script type=\"math/tex; mode=display\">P'(2x_{M}-\\alpha,2y_{M}-\\beta)</script></blockquote>\n","more":"<hr>\n<h3 id=\"问题解决\"><a href=\"#问题解决\" class=\"headerlink\" title=\"问题解决\"></a>问题解决</h3><p>​    作$P$点关于$l$的对称点$P’$,并过$PP’$点作直线$l_{2}$,如下图:</p>\n<p><img src=\"https://s1.ax1x.com/2020/08/01/aGm0nP.png\" style=\"zoom:15%;\" /></p>\n<p>​    可知直线$l_{2}$垂直平分$l$,令$l_{2}$交$l$于$M$,只要计算出$M$点的坐标即可通过<span id=\"inline-blue\">中点坐标公式</span>计算出$P’$的坐标</p>\n<blockquote>\n<p><strong>中点坐标公式</strong></p>\n<p>若$M$是$P$与$P’$的中点,则$M$点满足:</p>\n<script type=\"math/tex; mode=display\">M=\\frac{P+P'}{2}</script><p>此式中的字母表示该点的相应坐标(或者说表示从原点到该点的向量),此式在任意维度的坐标系中都成立.</p>\n</blockquote>\n<p>​    我们知道互相垂直的两条直线的斜率互为负倒数,所以由$l$的斜率为 $-\\frac{A}{B}$ ,可以知道 $l_{2}$ 的斜率 $k_{PP’}= \\frac{B}{A}$</p>\n<p>​    所以$l_{2}$的点斜式为 $l_{2} :y-B=\\frac{B}{A}(x-\\alpha )$,把点斜式化为一般式并与$l$联立得:</p>\n<script type=\"math/tex; mode=display\">\\left\\{\\begin{matrix} \n  Bx-Ay+a +(A\\beta -B\\alpha )=0 \\\\  \n  Ax+By+C=0 \n\\end{matrix}\\right.</script><p>​    解这个方程组,结果即为$M$的坐标.</p>\n<p>方程组的解为:</p>\n<script type=\"math/tex; mode=display\">x=\\frac{B^{2}\\alpha -AC-AB\\beta }{A^{2}+B^{2}}\ny=\\frac{A^{2}\\beta-BC-AB\\alpha }{A^{2}+B^{2}}</script><p>则$M$点的坐标为:</p>\n<script type=\"math/tex; mode=display\">M(\\frac{B^{2}\\alpha -AC-AB\\beta }{A^{2}+B^{2}}\n,\\frac{A^{2}\\beta-BC-AB\\alpha }{A^{2}+B^{2}}  )</script><p>带入中点坐标公式,得$P’$的坐标为:</p>\n<script type=\"math/tex; mode=display\">P'(2x_{M}-\\alpha,2y_{M}-\\beta)</script><h3 id=\"总结\"><a href=\"#总结\" class=\"headerlink\" title=\"总结\"></a>总结</h3><blockquote>\n<p><span id=\"inline-purple\">垂足坐标公式</span></p>\n<script type=\"math/tex; mode=display\">M(\\frac{B^{2}\\alpha -AC-AB\\beta }{A^{2}+B^{2}}\n,\\frac{A^{2}\\beta-BC-AB\\alpha }{A^{2}+B^{2}}  )</script><p><span id=\"inline-purple\">对称点坐标公式</span></p>\n<script type=\"math/tex; mode=display\">P'(2x_{M}-\\alpha,2y_{M}-\\beta)</script></blockquote>","categories":[{"name":"数学","path":"api/categories/数学.json"}],"tags":[{"name":"数学公式","path":"api/tags/数学公式.json"}]}